chrome_headless/__init__.py
chrome_headless/browser.py
chrome_headless/testcase.py
chrome_headless/util.py
chrome_headless/webview.py
chrome_headless_browser-0.12.0.dist-info/METADATA
chrome_headless_browser-0.12.0.dist-info/WHEEL
chrome_headless_browser-0.12.0.dist-info/top_level.txt
chrome_headless_browser-0.12.0.dist-info/RECORD
