Metadata-Version: 2.1
Name: chrome-headless-browser
Version: 0.12.0
Summary: UNKNOWN
Home-page: UNKNOWN
Author: Tencent
License: Copyright(c)2010-2022 Tencent All Rights Reserved. 
Platform: UNKNOWN
Requires-Dist: Pillow
Requires-Dist: qt4w
Requires-Dist: chrome-master
Requires-Dist: qtaf
